Workbook
Name Account_Endorse: 'Ref Select'!$A$1:$A$72
Name Attitude: 'Ref Select'!$P$2:$P$5
Name Check: 'Ref Select'!$W$2:$W$3
Name Choosing: 'Ref Select'!$I$1:$I$15
Name ClientDispo: 'Ref Select'!$T$2:$T$5
Name Course: 'Ref Select'!$H$1:$H$43
Name CPA: 'Ref Select'!$V$2:$V$5
Name Degree: 'Ref Select'!$G$1:$G$10
Name Essay: 'Ref Select'!$Q$2:$Q$5
Name Gender: 'Ref Select'!$C$1:$C$3
Name HOLDREJECT: 'Ref Select'!$N$2:$N$21
Name JO: 'Ref Select'!$AF$1:$AF$36
Name Number: 'Ref Select'!$E$2:$E$17
Name OPSDispo: 'Ref Select'!$S$2:$S$6
Name OpsInter: 'Ref Select'!$S$2:$S$6
Name PA: 'Ref Select'!$O$2:$O$6
Name Reason: 'Ref Select'!$X$2:$X$22
Name Recomendation: 'Ref Select'!$M$2:$M$7
Name Source_Applicant: 'Ref Select'!$B$1:$B$28
Name Transpo: 'Ref Select'!$K$1:$K$10
Name Verbal: 'Ref Select'!$R$2:$R$5
Name YESNO: 'Ref Select'!$D$2:$D$4
Name YNN: 'Ref Select'!$J$2:$J$4

Sheet For HR use only
B1: Form>> Autofill based on Recruitment form | C1: Details | E1: QB Form | F1: Staff Requisitions- Autofilled? | G1: Remarks | J1: Applicants :
B2: Last Name | C2: =IF(ISBLANK('Personal Information'!A8),"",'Personal Information'!A8) | F2: Current Day
B3: Maiden Name | C3: =IF(OR('Personal Information'!C8="N/A",'Personal Information'!C8="NA"),"",IF(ISBLANK('Personal Information'!C8),"",'Personal Information'!C8)) | F3: Requisition Month | J3: Applicant Background Form | K3: Details | L3: Remarks
B4: First Name | C4: =IF(ISBLANK('Personal Information'!E8),"",'Personal Information'!E8) | F4: Color | J4: Job Opening # | K4: 295 | L4: Manual- Required to fill
B5: Middle Name | C5: =IF(ISBLANK('Personal Information'!G8),"",'Personal Information'!G8) | F5: Reviewed by Talent Acquisition: | J5: Current Day | K5: 44498 | L5: Enter date manually
B6: Nickname | C6: =IF(ISBLANK('Personal Information'!I8),"",'Personal Information'!I8) | F6: Job Title: * | J6: Recruiting For: | K6: Senior Accountant | L6: Manual- Required to fill
B7: Present Address | C7: =IF(ISBLANK('Personal Information'!A10),"",'Personal Information'!A10) | F7: Grade Level | J7: Account endorsed to | K7: Tony Auto Group | L7: Manual- Required to Select
B8: Permanent Address | C8: =IF(ISBLANK('Personal Information'!F10),"",'Personal Information'!F10) | F8: Other Position Titles | J8: Position: | K8: Senior Accountant | L8: Manual- Required to fill
B9: Contact Number(s) | C9: =IF(ISBLANK('Personal Information'!A19),"",'Personal Information'!A19) | F9: Assignment/Client: * | J9: Application Date | K9: 44468 | L9: Enter date manually
B10: Email Address | C10: =IF(ISBLANK('Personal Information'!F19),"",'Personal Information'!F19) | F10: Number of Job openings | J10: Source of Applicant * | K10: Jobstreet | L10: Manual- Required to Select
B11: Current Monthly Salary | C11: =IF(ISBLANK('Personal Information'!C20),"",'Personal Information'!C20) | F11: Search Action Level * | J11: =IF($K$10="Indeed.com","Sponsored?*",_xlfn.IFNA(IF($K$10=VLOOKUP($K$10,'Ref Select'!$U$2:$U$9,1,0),"Referred by:*",""),"")) | L11: Manual- Required to fill if referred, Select if sponsor
B12: Expected Salary | C12: =IF(ISBLANK('Personal Information'!C21),"",'Personal Information'!C21) | F12: Location Authorized * | J12: Last Name * | K12: =IF(OR(C2=0,C2=""),"",C2) | L12: Autofill from Personal information
B13: Date Available (please specify Notice Period) | C13: =IF(ISBLANK('Personal Information'!C22),"",'Personal Information'!C22) | F13: Why Urgent or Expedite?* | J13: First Name * | K13: =IF(OR(C4=0,C4=""),"",C4) | L13: Autofill from Personal information
B14: The following conditions may be required at some point in your employment. Are you amenable to working: | F14: Position Needed by* | J14: Middle Name | K14: =IF(OR(C5=0,C5=""),"",C5) | L14: Autofill from Personal information
B15: Shifts | F15: Direct Supervisor: | J15: Nick Name | K15: =IF(OR(C6=0,C6=""),"",C6) | L15: Autofill from Personal information
B16: Graveyard Shift | C16: =IF(ISBLANK('Personal Information'!G23),"",'Personal Information'!G23) | F16: Department: | J16: Gender * | K16: =IF(OR(C28=0,C28=""),"",C28) | L16: Autofill from Personal information
B17: Rotation Schedule | C17: =IF(ISBLANK('Personal Information'!G24),"",'Personal Information'!G24) | F17: Department Head: | J17: Date of Birth | K17: =IF(OR(C26=0,C26=""),"",C26 ) | L17: Autofill from Personal information
B18: Overtime | C18: =IF(ISBLANK('Personal Information'!G25),"",'Personal Information'!G25) | F18: Search Classification * | J18: Age (In Years) | K18: =IF(ISTEXT(K17),"",(YEAR(TODAY())-YEAR(K17))) | L18: Calculated field
B19: Holidays | C19: =IF(ISBLANK('Personal Information'!G26),"",'Personal Information'!G26) | F19: Date Open: | J19: Head of Household * | K19: =IF(ISBLANK(VLOOKUP($J19,'Additional Information'!$A:$B,2,0)),"",_xlfn.IFNA(VLOOKUP($J19,'Additional Information'!$A:$B,2,0),"")) | L19: Autofill from Additional information
B20: Type of Employment | C20: =IF(ISBLANK('Personal Information'!H21),"",'Personal Information'!H21) | F20: Target Hire Date: | J20: Number of Dependents * | K20: =IF(ISBLANK(VLOOKUP($J20,'Additional Information'!$A:$B,2,0)),"",_xlfn.IFNA(VLOOKUP($J20,'Additional Information'!$A:$B,2,0),"")) | L20: Autofill from Additional information
B21: How did you know about us? | C21: =IF('Personal Information'!H23="others","Others | "&" "&SUBSTITUTE('Personal Information'!H25,"Please Specify: ",""),'Personal Information'!H23) -> 0 | F21: Planned Search Duration (Days) | J21: Date Willing to Start * | K21: =IF(ISBLANK(VLOOKUP($J21,'Additional Information'!$A:$B,2,0)),"",_xlfn.IFNA(VLOOKUP($J21,'Additional Information'!$A:$B,2,0),"")) | L21: Autofill from Additional information
B22: Government Numbers | F22: Base Compensation (Min): * | J22: Resume Attachment | K22: Yes | L22: Manual- Required to Select
B23: SSS Number | C23: =IF(ISBLANK('Personal Information'!C24),"",'Personal Information'!C24) | F23: Grade Midpoint | J23: Start Date on Last Job | K23: =IF(ISBLANK(VLOOKUP($J23,'Additional Information'!$A:$B,2,0)),"",_xlfn.IFNA(VLOOKUP($J23,'Additional Information'!$A:$B,2,0),"")) | L23: Autofill from Additional information | N23: Background color legend:
B24: Tin | C24: =IF(ISBLANK('Personal Information'!C25),"",'Personal Information'!C25) | F24: Average Salary in Account * | J24: End Date on Last Job | K24: =IF(ISBLANK(VLOOKUP($J24,'Additional Information'!$A:$B,2,0)),"",_xlfn.IFNA(VLOOKUP($J24,'Additional Information'!$A:$B,2,0),"")) | L24: Autofill from Additional information | N24: GREY : Manual Entry of data/details
B25: Pag Ibig | C25: =IF(ISBLANK('Personal Information'!C26),"",'Personal Information'!C26) | F25: Highest Salary in Account * | J25: Still with Last Employer | K25: =IF(ISBLANK(VLOOKUP($J25,'Additional Information'!$A:$B,2,0)),"",_xlfn.IFNA(VLOOKUP($J25,'Additional Information'!$A:$B,2,0),"")) | L25: Autofill from Additional information | N25: WHITE: Auto fill based on Personal information tab
B26: Date of Birth | C26: =IF(ISBLANK('Personal Information'!A28),"",'Personal Information'!A28) | F26: Salary Offered | J26: Application Attachment | K26: Yes | L26: Manual- Required to Select
B27: Citizenship | C27: =IF(ISBLANK('Personal Information'!C28),"",'Personal Information'!C28) | F27: Referral Bonus | J27: Number of Jobs in Last 3 Years * | K27: =IF(ISBLANK(VLOOKUP($J27,'Additional Information'!$A:$B,2,0)),"",_xlfn.IFNA(VLOOKUP($J27,'Additional Information'!$A:$B,2,0),"")) | L27: Autofill from Additional information
B28: Gender | C28: =IF(ISBLANK('Personal Information'!F28),"",'Personal Information'!F28) | F28: Hiring Bonus: | J28: Reason for Leaving Last Job | K28: =IF(ISBLANK(VLOOKUP($J28,'Additional Information'!$A:$B,2,0)),"",_xlfn.IFNA(VLOOKUP($J28,'Additional Information'!$A:$B,2,0),"")) | L28: Autofill from Additional information
B29: Civil Status | C29: =IF(ISBLANK('Personal Information'!H28),"",'Personal Information'!H28) | F29: Bonus Potential: | J29: Notice Period (Days) | K29: =IF(ISBLANK(VLOOKUP($J29,'Additional Information'!$A:$B,2,0)),"",_xlfn.IFNA(VLOOKUP($J29,'Additional Information'!$A:$B,2,0),"")) | L29: Autofill from Additional information
B30: EDUCATIONAL BACKGROUND | F30: Planned Schedule: | J30: High School Graduate | K30: =IF(ISBLANK(VLOOKUP($J30,'Additional Information'!$A:$B,2,0)),"",_xlfn.IFNA(VLOOKUP($J30,'Additional Information'!$A:$B,2,0),"")) | L30: Autofill from Additional information
B31: Secondary | F31: Direct Experience Field | J31: Attended College | K31: =IF(ISBLANK(VLOOKUP($J31,'Additional Information'!$A:$B,2,0)),"",_xlfn.IFNA(VLOOKUP($J31,'Additional Information'!$A:$B,2,0),"")) | L31: Autofill from Additional information
B32: Degree/Course | C32: =IF(ISBLANK('Personal Information'!G30),"",'Personal Information'!G30) | F32: Years Direct Experience Required | J32: College Graduate | K32: =IF(ISBLANK(VLOOKUP($J32,'Additional Information'!$A:$B,2,0)),"",_xlfn.IFNA(VLOOKUP($J32,'Additional Information'!$A:$B,2,0),"")) | L32: Autofill from Additional information
B33: Inclusive Dates | C33: =IF(ISBLANK('Personal Information'!I30),"",'Personal Information'!I30) | F33: Job Description | J33: Degree Obtained | K33: =IF(ISBLANK(VLOOKUP($J33,'Additional Information'!$A:$B,2,0)),"",_xlfn.IFNA(VLOOKUP($J33,'Additional Information'!$A:$B,2,0),"")) | L33: Autofill from Additional information
B34: Name | C34: =IF(ISBLANK('Personal Information'!B31),"",'Personal Information'!B31) | F34: Required Qualifications: * | J34: Major Course of Study | K34: =IF(ISBLANK(VLOOKUP($J34,'Additional Information'!$A:$B,2,0)),"",_xlfn.IFNA(VLOOKUP($J34,'Additional Information'!$A:$B,2,0),"")) | L34: Autofill from Additional information
B35: Address | C35: =IF(ISBLANK('Personal Information'!B32),"",'Personal Information'!B32) | F35: Role and Responsibilities: | J35: =IF(K34="Accounting","Passed CPA Exam?*","") | K35: YES | L35: Manual- Required to fill
B36: Contact Info | C36: =IF(ISBLANK('Personal Information'!B33),"",'Personal Information'!B33) | F36: Client Endorsement Required * | J36: Special Skills or Qualifications | K36: =IF(ISBLANK(VLOOKUP($J36,'Additional Information'!$A:$B,2,0)),"",_xlfn.IFNA(VLOOKUP($J36,'Additional Information'!$A:$B,2,0),"")) | L36: Autofill from Additional information
B37: Collegiate | F37: Billable to Client | J37: Why Choosing Connext? | K37: =IF(ISBLANK(VLOOKUP($J37,'Additional Information'!$A:$B,2,0)),"",_xlfn.IFNA(VLOOKUP($J37,'Additional Information'!$A:$B,2,0),"")) | L37: Autofill from Additional information
B38: Degree/Course | C38: =IF(ISBLANK('Personal Information'!G34),"",'Personal Information'!G34) | F38: Degree Required? | J38: Travel Time to our Office (Min) * | K38: =IF(ISBLANK(VLOOKUP($J38,'Additional Information'!$A:$B,2,0)),"",_xlfn.IFNA(VLOOKUP($J38,'Additional Information'!$A:$B,2,0),"")) | L38: Autofill from Additional information
B39: Inclusive Dates | C39: =IF(ISBLANK('Personal Information'!I34),"",'Personal Information'!I34) | F39: Specify Field(s)* | J39: Own Transportation | K39: =IF(ISBLANK(VLOOKUP($J39,'Additional Information'!$A:$B,2,0)),"",_xlfn.IFNA(VLOOKUP($J39,'Additional Information'!$A:$B,2,0),"")) | L39: Autofill from Additional information
B40: Name | C40: =IF(ISBLANK('Personal Information'!B35),"",'Personal Information'!B35) | F40: Fresh Grad Ok? | J40: =IF($K39="NO", "Mode of Transportation*","") | K40: =IF(ISBLANK(VLOOKUP($J40,'Additional Information'!$A:$B,2,0)),"",_xlfn.IFNA(VLOOKUP($J40,'Additional Information'!$A:$B,2,0),"")) | L40: Autofill from Additional information
B41: Address | C41: =IF(ISBLANK('Personal Information'!B36),"",'Personal Information'!B36) | F41: Equipment Required * | J41: =IF($K39="NO","Number of Vehicles*","") | K41: =IF(ISBLANK(VLOOKUP($J41,'Additional Information'!$A:$B,2,0)),"",_xlfn.IFNA(VLOOKUP($J41,'Additional Information'!$A:$B,2,0),"")) | L41: Autofill from Additional information
B42: Contact Info | C42: =IF(ISBLANK('Personal Information'!B37),"",'Personal Information'!B37) | F42: Account Credentials * | J42: Valid Passport * | K42: =IF(ISBLANK(VLOOKUP($J42,'Additional Information'!$A:$B,2,0)),"",_xlfn.IFNA(VLOOKUP($J42,'Additional Information'!$A:$B,2,0),"")) | L42: Autofill from Additional information
B43: Post Graduate/Professional/Others | F43: Peripherals Needed * | J43: =IF(K42="YES","Valid US Visa*","") | K43: =IF(ISBLANK(VLOOKUP($J43,'Additional Information'!$A:$B,2,0)),"",_xlfn.IFNA(VLOOKUP($J43,'Additional Information'!$A:$B,2,0),"")) | L43: Autofill from Additional information
B44: Degree/Course | C44: =IF(ISBLANK('Personal Information'!G38),"",'Personal Information'!G38) | F44: Selection Questions | J44: =IF(K42="YES","Former OFW*","") | K44: =IF(ISBLANK(VLOOKUP($J44,'Additional Information'!$A:$B,2,0)),"",_xlfn.IFNA(VLOOKUP($J44,'Additional Information'!$A:$B,2,0),"")) | L44: Autofill from Additional information
B45: Inclusive Dates | C45: =IF(ISBLANK('Personal Information'!G39),"",'Personal Information'!G39) | F45: REQUIRED QUESTIONS | J45: Current (Base) Salary * | K45: =IF(ISBLANK(VLOOKUP($J45,'Additional Information'!$A:$B,2,0)),0,_xlfn.IFNA(VLOOKUP($J45,'Additional Information'!$A:$B,2,0),"")) -> 0 | L45: Autofill from Additional information
B46: Name | C46: =IF(ISBLANK('Personal Information'!B39),"",'Personal Information'!B39) | F46: Screening Question 1* | J46: Desired Salary * | K46: =IF(ISNUMBER(IF(ISBLANK(VLOOKUP($J46,'Additional Information'!$A:$B,2,0)),"",_xlfn.IFNA(VLOOKUP($J46,'Additional Information'!$A:$B,2,0),""))),IF(ISBLANK(VLOOKUP($J46,'Additional Information'!$A:$B,2,0)),"",_xlfn.IFNA(VLOOKUP($J46,'Additional Information'!$A:$B,2,0),"")),0) -> 0 | L46: Autofill from Additional information
B47: Address | C47: =IF(ISBLANK('Personal Information'!B40),"",'Personal Information'!B40) | F47: What resources do you use (e.g. forums, websites and books) to keep up-to-date with engineering trends? | J47: Offered (Base) Salary | K47: 45000 | L47: Manual Entry
B48: Contact Info | C48: =IF(ISBLANK('Personal Information'!B41),"",'Personal Information'!B41) | F48: Screening Question 2* | J48: Contact Number: | K48: =IF(OR(C9=0,C9=""),"",C9 ) | L48: Autofill from Personal information
B49: FAMILY HISTORY | F49: What types of problems have you encountered most often in operational systems after deployment? | J49: Contact Email: | K49: =IF(OR(C10=0,C10=""),"",C10 ) | L49: Autofill from Personal information
B50: Father | F50: Screening Question 3*
B51: Name | C51: =IF(ISBLANK('Personal Information'!B$44),"",'Personal Information'!B$44) | F51: Describe a time when you had to make a presentation. How did you manage to explain technical details to a non-technical audience?
B52: Occupation | C52: =IF(ISBLANK('Personal Information'!F$44),"",'Personal Information'!F$44) | F52: OPTIONAL QUESTIONS
B53: Employer/School | C53: =IF(ISBLANK('Personal Information'!H$44),"",'Personal Information'!H$44) | F53: Screening Question 4
B54: Mother | F54: Screening Question 5 | J54: Recruitment Screening
B55: Name | C55: =IF(ISBLANK('Personal Information'!B$45),"",'Personal Information'!B$45) | F55: Screening Question 6 | J55: Years Direct Experience | K55: 21 | L55: Manual- Required to fill
B56: Occupation | C56: =IF(ISBLANK('Personal Information'!F$45),"",'Personal Information'!F$45) | F56: Screening Question 7 | J56: =IFERROR(VLOOKUP((1&$K$4)*1,'Ref Select'!$AB:$AC,2,0),"-") -> How would you rate your key competencies for this job? | K56: 10 | L56: Manual- Required to fill
B57: Employer/School | C57: =IF(ISBLANK('Personal Information'!H$45),"",'Personal Information'!H$45) | F57: Screening Question 8 | J57: =IFERROR(VLOOKUP((2&$K$4)*1,'Ref Select'!$AB:$AC,2,0),"-") -> How will you keep your POCs updated with your tasks when working remotely? | L57: Manual- Required to fill
B58: Brothers/Sisters | F58: Screening Question 9 | J58: =IFERROR(VLOOKUP((3&$K$4)*1,'Ref Select'!$AB:$AC,2,0),"-") -> Are willing to change shift in case the client requires it? | K58: No | L58: Manual- Required to fill
B59: Name | C59: =IF(ISBLANK('Personal Information'!B$46),"",'Personal Information'!B$46) | F59: Screening Question 10 | J59: =IFERROR(VLOOKUP((4&$K$4)*1,'Ref Select'!$AB:$AC,2,0),"-") -> - | L59: Manual- Required to fill
B60: Occupation | C60: =IF(ISBLANK('Personal Information'!F$46),"",'Personal Information'!F$46) | F60: Search Detail | J60: Recruiter Recommendation | K60: Hire | L60: Manual- Required to Select
B61: Employer/School | C61: =IF(ISBLANK('Personal Information'!H$46),"",'Personal Information'!H$46) | F61: Actual Fill Date | J61: =IF(K60="HIRE","Interview Scheduled","") -> Interview Scheduled | K61: 44498 | L61: Enter date manually
B62: Brothers/Sisters1 | F62: Month | J62: =IF(OR($K$60="HOLD",$K$60="Reject and Pool"),$K$60&" | Explain Reason:*","") | L62: =IF(K60="Hire","","Manual- Required to Select ")
B63: Name | C63: =IF(ISBLANK('Personal Information'!B$47),"",'Personal Information'!B$47) | F63: Actual Fill Duration | J63: Recruiter Comments2 | K63: NA | L63: Manual
B64: Occupation | C64: =IF(ISBLANK('Personal Information'!F$47),"",'Personal Information'!F$47) | F64: Search Status *
J65: =IF($K$60="HIRE","Final Interview and Selection Status","") -> Final Interview and Selection Status
J66: =IF($K$60="HIRE","On Time for Appointment?","") -> On Time for Appointment? | L66: Manual- Required to Select
J67: =IF($K$60="HIRE","Professional Appearance?","") -> Professional Appearance? | L67: Manual- Required to Select
B68: Employer/School | C68: =IF(ISBLANK('Personal Information'!H$47),"",'Personal Information'!H$47) | F68: Current Search Days | J68: =IF($K$60="HIRE","Attitute Towards Position?","") -> Attitute Towards Position? | L68: Manual- Required to Select
B69: Brothers/Sisters2 | F69: Search Duration | J69: =IF($K$60="HIRE","Intends to Stay Long-Term?","") -> Intends to Stay Long-Term? | L69: Manual- Required to Select
B70: Name | C70: =IF(ISBLANK('Personal Information'!B$48),"",'Personal Information'!B$48) | F70: Days Remaining | J70: =IF($K$60="HIRE",IF(K27>2,"Stability Question",""),"") -> Stability Question
B71: Occupation | C71: =IF(ISBLANK('Personal Information'!F$48),"",'Personal Information'!F$48) | F71: Avg Daily Rate | J71: =IF($K$60="HIRE",IF(K27>2,"Stability Response*",""),"") -> Stability Response* | L71: Manual Entry
B72: Employer/School | C72: =IF(ISBLANK('Personal Information'!H$48),"",'Personal Information'!H$48) | F72: Search Revenue Php | J72: =IF($K$60="HIRE",IF(K27>2,"Why have you changed jobs so often?",""),"") -> Why have you changed jobs so often? | L72: Manual Entry
B73: Brothers/Sisters3 | J73: =IF($K$60="HIRE","Is there any risk of your returning your previous employer?","") -> Is there any risk of your returning your previous employer? | L73: Manual Entry
B74: Name | C74: =IF(ISBLANK('Personal Information'!B$49),"",'Personal Information'!B$49) | J74: =IF($K$60="HIRE",IF(_xlfn.IFNA(VLOOKUP(K28,'Ref Select'!$X$2:$Y$22,2,0),0)=1,"","Return Response"),"") -> Return Response | L74: Manual Entry
B75: Occupation | C75: =IF(ISBLANK('Personal Information'!F$49),"",'Personal Information'!F$49) | J75: =IF($K$60="HIRE",IF(K44="YES","OFW Risk Question",""),"")
B76: Employer/School | C76: =IF(ISBLANK('Personal Information'!H$49),"",'Personal Information'!H$49) | J76: =IF($K$60="HIRE",IF(K44="YES","Do you intend to do another relocation to a foreign country?",""),"") | L76: Manual Entry
B77: Brothers/Sisters4 | J77: =IF($K$60="HIRE","Salary Variance Response*","") -> Salary Variance Response*
B78: Name | C78: =IF(ISBLANK('Personal Information'!B$50),"",'Personal Information'!B$50) | J78: =IF($K$60="HIRE","Are you concerned that our offer is less than your current compensation?","") -> Are you concerned that our offer is less than your current compensation? | L78: Manual Entry
B79: Occupation | C79: =IF(ISBLANK('Personal Information'!F$50),"",'Personal Information'!F$50) | J79: =IF($K$60="HIRE","Essay Quality","") -> Essay Quality | L79: Manual- Required to Select
B80: Employer/School | C80: =IF(ISBLANK('Personal Information'!H$50),"",'Personal Information'!H$50) | J80: =IF($K$60="HIRE","Vebal Communication","") -> Vebal Communication | L80: Manual- Required to Select
B81: Spouse | J81: =IF($K$60="HIRE","Ops Interview Schedule","") -> Ops Interview Schedule | L81: Enter date manually
B82: Name | C82: =IF(ISBLANK('Personal Information'!B$51),"",'Personal Information'!B$51) | J82: =IF($K$60="HIRE","Ops Interview Disposition","") -> Ops Interview Disposition | L82: Manual- Required to Select
B83: Occupation | C83: =IF(ISBLANK('Personal Information'!F$51),"",'Personal Information'!F$51) | J83: =IF($K$60="HIRE","Ops Remarks","") -> Ops Remarks | L83: Manual Entry
B84: Employer/School | C84: =IF(ISBLANK('Personal Information'!H$51),"",'Personal Information'!H$51)
B85: Child/Children
B86: Name | C86: =IF(ISBLANK('Personal Information'!B$52),"",'Personal Information'!B$52)
B87: Occupation | C87: =IF(ISBLANK('Personal Information'!F$52),"",'Personal Information'!F$52)
B88: Employer/School | C88: =IF(ISBLANK('Personal Information'!H$52),"",'Personal Information'!H$52)
B90: EMPLOYMENT HISTORY
B91: Company Name | C91: =IF(ISBLANK('Employment History'!$B2),"",'Employment History'!$B2)
B92: Contact Details (Tel #, Email) | C92: =IF(ISBLANK('Employment History'!$G2),"",'Employment History'!$G2)
B93: Address | C93: =IF(ISBLANK('Employment History'!$B3),"",'Employment History'!$B3)
B94: Position | C94: =IF(ISBLANK('Employment History'!$B4),"",'Employment History'!$B4)
B95: Inclusive dates | C95: =IF(ISBLANK('Employment History'!$E9),"",'Employment History'!$E9)
B96: Monthly Salary | C96: =IF(ISBLANK('Employment History'!$H4),"",'Employment History'!$H4)
B97: Reason for leaving | C97: =IF(ISBLANK('Employment History'!$C5),"",'Employment History'!$C5)
B98: Company Name | C98: =IF(ISBLANK('Employment History'!$B7),"",'Employment History'!$B7) -> Taskus Inc
B99: Contact Details (Tel #, Email) | C99: =IF(ISBLANK('Employment History'!$G7),"",'Employment History'!$G7)
B100: Address | C100: =IF(ISBLANK('Employment History'!$B8),"",'Employment History'!$B8)
B101: Position | C101: =IF(ISBLANK('Employment History'!$B9),"",'Employment History'!$B9)
...

Sheet How to
B2: How to fill the field details
B3: Please do rename or SAVE as for the file name with the sample format [Sample: Juan_Luna_DelaCruz_Recruitment Form]
B4: Fill in only blank fields below or after the question field
B5: If not related, leave blank or enter NA
B6: Enter only whole numbers for contact numbers, government IDs and other fields with numbers
B7: Birthdate enter MMM DD, YYYY [Sample: Jan 01, 2000]

Sheet Personal Information
A6: PERSONAL INFORMATION
A7: Last Name | C7: Maiden Name | E7: First Name | G7: Middle Name | I7: Nickname
A9: Present Address | F9: Permanent Address
A18: Contact Number(s) | F18: Email Address
A20: Current Monthly Salary | E20: The following conditions may be required at some point in your employment. Are you amenable to working: | H20: Type of Employment
A21: Expected Salary
A22: Date Available (please specify Notice Period | E22: Shifts | H22: How did you know about us?
A23: Government Numbers | E23: Graveyard Shift
A24: SSS Number | E24: Rotation Schedule
A25: Tin | E25: Overtime | H25: Please Specify: Jobsteet.com
A26: Pag Ibig | E26: Holidays
A27: Date of Birth | C27: Citizenship | F27: Gender | H27: Civil Status
A29: EDUCATIONAL BACKGROUND | G29: Degree/Course | I29: Inclusive Dates
A30: Secondary
A31: Name
A32: Address
A33: Contact Info
A34: Collegiate
A35: Name
A36: Address
A37: Contact Info
A38: Post Graduate/Professional/Others
A39: Name
A40: Address
A41: Contact Info
A42: FAMILY HISTORY
B43: Name | F43: Occupation | H43: Employer/School
A44: Father
A45: Mother
A46: Brothers/Sisters
A51: Spouse
A52: Child/Children

Sheet Employment History
A1: EMPLOYMENT HISTORY
A2: Company Name | E2: Contact Details (Tel #, Email)
A3: Address
A4: Position | D4: Inclusive dates | G4: Monthly Salary
A5: Reason for leaving
A7: Company Name | B7: Taskus Inc | E7: Contact Details (Tel #, Email)
A8: Address
A9: Position | D9: Inclusive dates | G9: Monthly Salary
A10: Reason for leaving
A12: Company Name | E12: Contact Details (Tel #, Email)
A13: Address
A14: Position | D14: Inclusive dates | G14: Monthly Salary
A15: Reason for leaving
A16: TRAINING AND CERTIFICATION
A17: Course/Title | C17: Description | E17: Inclusive dates | G17: Training Institution
A22: SKILLS AND INTEREST
A23: Softwate Knowledge | E23: Equipment Knowledge
A24: Typing | E24: Professional Licenses and Memberships
A25: Language Fluency
A26: Please rate 1-5, 5 being the highest | C26: Spoken | D26: Written | E26: Other Skills (please specify)
A27: English
E28: Have you ever had any International exposure/travel Experience? (Please Specify)
A32: OTHERS
A33: Are you related to any person presently connnected with Connext? | H33: No
A34: Name and Relationship
A35: Have you had any criminal or civil liability? | H35: No
A36: Please specify
A37: REFERRALS
A38: Name | C38: Phone # | F38: Email Address
A44: CHARACTER REFERENCE
A45: PREVIOUS EMPLOYMENT
A46: Name | C46: Company | E46: Position | G46: Contact No(s)
A50: COLLEGE DEAN / SCHOOL REGISTRAR
A51: Name | C51: Company | E51: Position | G51: Contact No(s)
A54: Reference #

Sheet Essay
A1: Please write a short narrative on the question: (min, 100 words)
A2: Compose in no more than 100 words everything you want us to know about you. Include your work behavior strengths ans weaknesses, your expectations towards the company, your office mates and superiors. State also your future plans and goals in life (Alt + Enter to make another paragraph)
A25: OTHERS
A26: Are you related to any person presently connnected with Connext? | H26: No
A27: Name and Relationship
A28: In case of Emergency Contact Information
A29: Have you had any criminal or civil liability? | H29: No
A30: Please specify
A31: REFERRALS
A32: Name | C32: Phone # | F32: Email Address

Sheet Additional Information
A1: Additional information | * Required
A2: Head of Household *
A3: Number of Dependents *
A4: Date Willing to Start *
A5: Start Date on Last Job
A6: End Date on Last Job
A7: Still with Last Employer
A8: Number of Jobs in Last 3 Years *
A9: Reason for Leaving Last Job
A10: Notice Period (Days)
A11: High School Graduate
A12: Attended College
... A19: Own Transportation
A20: =IF($B19="NO", "Mode of Transportation*","-") -> -
A21: =IF($B19="NO","Number of Vehicles*","--") -> --
A22: Valid Passport *
A23: =IF(B22="YES","Valid US Visa*","")
A24: =IF(B22="YES","Former OFW*","")
A25: Current (Base) Salary * | B25: ='Personal Information'!C20 -> 0
A26: Desired Salary * | B26: ='Personal Information'!C21 -> 0

Sheet Ref Select
A1: Account endorsed to | B1: Source of Applicant * | C1: Gender * | D1: Head of Household * | E1: Number of Dependents * Number of Dependents * Number of Dependents * | F1: Number of Jobs in Last 3 Years | G1: Degree Obtained | H1: Major Course of Study | I1: Why Choosing Connext? | J1: Own Transportation | K1: Mode of Transportation* | L1: Valid Passport * | M1: Recruiter Recommendation | N1: Explain Reason: | O1: Professional Appearance? | P1: Attitute Towards Position? | Q1: Essay Quality | R1: Vebal Communication | S1: Ops Interview Disposition | T1: Client Interview Disposition | U1: Referral | V1: Passed CPA | W1: Check | X1: Reason for Leaving Last Job | Y1: No No "Return Response" | AA1: =AB1 -> 286 | AB1: =RIGHT(AC1,3)*1 -> 286 | AC1: Job Opening #286 | AF1: Job Opening
A2: ACE MEDICAL | B2: Academic Referrals | C2: Female | D2: Yes | E2: 0 | F2: 0 | G2: Associates | H2: Accounting | I2: Benefits | J2: Yes | K2: Ride Share | L2: Yes | M2: Hire | N2: Better internal/external hire options | O2: Provocative | P2: Complaints and Conditions | Q2: Poorly Written | R2: Prefers to speak in Local Vernacular | S2: Reject | T2: Reject | U2: Academic Referrals | V2: YES | W2: ü | X2: Birth or Child Care | AC2: PROFESSIONAL QUESTIONS | AF2: 256
A3: Aiea Pediatric Dental Center | B3: CDC Clark | C3: Male | D3: No | E3: 1 | F3: 1 | G3: BA or BS | H3: Agriculture, Agriculture Operations, and Related Sciences | I3: Challenge | J3: No | K3: Jeepney | L3: No | M3: Hold | N3: Does Not Speak English | O3: Casual | P3: Hard to Tell | Q3: Some Errors, but Acceptable | R3: English with noticeable grammar errors | S3: Hold Pending Other Candidates | T3: Hold Pending Other Candidates | U3: Community Networking | V3: NO | X3: Comp/Benefits | AC3: Screening Question 1 | AF3: 283
A4: AKAMAI | B4: Community Networking | E4: 2 | F4: 2 | G4: Masters | H4: Architecture and Related Services | I4: Culture / Working Environment | K4: Bus | M4: Reject and Pool | N4: High risk points (Start SMART) | O4: Business or Smart Casual | P4: Enthusiastic | Q4: Well Written | R4: Clearly understandable | S4: Recommend to Client | T4: Ok to Hire | U4: Employee Referral (Unqualified) | V4: Not Eligible | X4: Company Sold/Merged/Closed | Y4: 1 | AB4: =(1&AB1)*1 -> 1286 | AC4: How do you handle pressure at work especially when meeting deadlines? | AF4: 286
A5: ALIKAI HEALTH LLC | B5: Craigslist | E5: 3 | F5: 3 | G5: CPA | H5: Area, Ethnic, Cultural, Gender, and Group Studies | I5: Facility | K5: Trike | M5: Client Evaluation Recommended | N5: Irrelevant skills or experience | O5: Business Attire | S5: Ok to Hire | U5: Employee Referral Program | X5: Contract Ended | AC5: Response | AF5: 290
A6: Aloha Wound Care | B6: Employee Referral (resigned) | E6: 4 | F6: 4 | G6: PHD | H6: Aviation | I6: Jobs within Field | K6: Taxi | N6: Lack of enthusiasm | U6: Headhunter/Partner | X6: Disagreed with Management | Y6: 1 | AC6: Screening Question 2 | AF6: 291
A7: Ambulnz | B7: Employee Referral (Unqualified) | E7: 5 | F7: 5 | G7: Other (See Special Skills) | H7: Biological and Biomedical Sciences | I7: Just Need a Job / Applied Various Places | K7: Grab | N7: Made unrealistic salary/pay demands | U7: Temp Agency | X7: FRESH GRADUATE | Y7: 1 | AB7: =(2&AB1)*1 -> 2286 | AC7: Are you amenable to work on mid shift or night shift? | AF7: 292
A8: American Electric | B8: Employee Referral Program | E8: 6 | F8: 6 | H8: Business | I8: Location or Convenience | K8: Multiple | N8: Negative comments about past employer | X8: Illness | AC8: Response | AF8: 293
A9: ASB | B9: Existing Employee | E9: 7 | F9: 7 | H9: Business, Management, Marketing, and Related Support Services | I9: Recognition and Growth | K9: Other | N9: Not able to supply references | X9: Job Not in Field | Y9: 1 | AC9: Screening Question 3 | AF9: 294
A10: Atlantic Broadband | B10: Facebook | E10: 8 | F10: 8 | H10: Communication, Journalism, and Related Programs | I10: Referred by Family or Friend | N10: Poor references | X10: NEW TO WORKFORCE | Y10: 1 | AB10: =(3&AB1)*1 -> 3286 | AC10: How comfortable are you working with foreign clients? | AF10: 296
A11: Brayn Consulting | B11: Flyer from Solicitor | E11: 9 | F11: 9 | H11: Communications Technologies/technicians and Support Services | I11: Reputation and Brand | N11: Poor test scores | X11: No Growth Opportunities | Y11: 1 | AC11: Response | AF11: 297
A12: Business Development | B12: Headhunter/Partner | E12: 10 | F12: 10 | H12: Computer and Information Sciences and Support Services | I12: Salary | N12: Poor verbal/written communication | X12: Personal Reasons | AF12: 298
A13: Connext Staff | B13: Indeed.com | E13: 11 | F13: 11 | H13: Construction Trades | I13: Working Hours | N13: Qualified - Will continue to interview candidates | X13: Relocation | AA13: =AB13 -> 256 | AB13: =RIGHT(AC13,3)*1 -> 256 | AC13: Job Opening #256 | AF13: 299
A14: Dougherty Laser Vision | B14: Internal/Transfer | E14: 12 | F14: 12 | H14: Education | N14: Showed up very late (no valid reason) | X14: Returned to School | AC14: PROFESSIONAL QUESTIONS | AF14: 300
A15: Dr. Wade Takenishi | B15: Job Fair or Open House | E15: 13 | F15: 13 | H15: Engineering | N15: Speaks English, but struggles | X15: Started Business | AC15: Screening Question 1 | AF15: 301
A16: ECA ADVISORS | B16: Jobstreet | E16: 14 | F16: 14 | H16: Engineering Technologies and Engineering-Related Fields | N16: Unable or Unwilling to meet pre-hire requirements | X16: STILL WITH LAST EMPLOYER | Y16: 1 | AB16: =(1&AB13)*1 -> 1256 | AC16: What resources do you use (e.g. forums, websites and books) to keep up-to-date with engineering trends? | AF16: 302
A17: EJDA Services Inc. | B17: LinkedIn | E17: 15 | F17: 15 | H17: English Language and Literature/letters | N17: Unable to follow job application directions | X17: Stressful Work | Y17: 1 | AC17: Response | AF17: 303
A18: Eleyae Systems | B18: Monster.com | H18: Family and Consumer Sciences/human Sciences | N18: Under or over qualified | X18: Terminated - Performance | Y18: 1 | AC18: Screening Question 2 | AF18: 304
A19: Financial Services | B19: OJT | H19: Foreign Languages, Literatures, and Linguistics | X19: Terminated - Policy Violation | Y19: 1 | AB19: =(2&AB13)*1 -> 2256 | AC19: What types of problems have you encountered most often in operational systems after deployment? | AF19: 305
A20: FinLync | B20: Public Referral | H20: Health Professions and Related Programs | X20: Travel Distance | AC20: Response | AF20: 306
A21: Great Falls | B21: Recruiting Database | H21: History | X21: Work Hours | AC21: Screening Question 3 | AF21: 307
A22: HAM | B22: Tarpulin | H22: Homeland Security, Law Enforcement, Firefighting | AB22: =(3&AB13)*1 -> 3256 | AC22: Describe a time when you had to make a presentation. How did you manage to explain technical details to a non-technical audience? | AF22: 308
A23: HappyDoors Property Management | B23: Temp Agency | H23: Human Services | AC23: Response | AF23: 309
A24: Hawaii Endodontics | B24: Walk-In | H24: Legal Professions and Studies | AF24: 310
A25: Hawaii Pacific | B25: Website | H25: Liberal Arts and Sciences Studies and Humanities | AA25: =AB25 -> 283 | AB25: =RIGHT(AC25,3)*1 -> 283 | AC25: Job Opening #283 | AF25: 311
A26: HAWKTREE | B26: Word of mouth | H26: Library Science | AC26: PROFESSIONAL QUESTIONS
A27: HEALTHCARE | B27: Workbank | H27: Mathematics and Statistics | AC27: Screening Question 1
A28: HI SMILE ORTH | H28: Mechanic and Repair Technologies/technicians | AB28: =(1&AB25)*1 -> 1283 | AC28: Are you amendable to work on Hawaii Hours?
A29: HIBH | H29: Military Technologies and Applied Sciences | AC29: Response
A30: Hicks Pension | H30: Multi/interdisciplinary Studies | AC30: Screening Question 2
A31: Honolulu Disposal Service Inc | H31: Natural Resources and Conservation | AB31: =(2&AB25)*1 -> 2283 | AC31: What is customer service for you?
A32: HR Services | H32: Parks, Recreation, Leisure, and Fitness Studies | AC32: Response
A33: HR/Admin | H33: Personal and Culinary Services | AC33: Screening Question 3
A34: Island Healthcare Solutions | H34: Philosophy and Religious Studies | AB34: =(3&AB25)*1 -> 3283 | AC34: Describe a time when you received bad customer service and how did you deal with it?
A35: Jack in the Box | H35: Physical Sciences | AC35: Response
A36: K&K | H36: Precision Production
A37: Kidshine Pediatric Dental Group | H37: Psychology | AA37: =AB37 -> 292 | AB37: =RIGHT(AC37,3)*1 -> 292 | AC37: Job Opening #292
A38: KOHA | H38: Science Technologies/technicians | AC38: PROFESSIONAL QUESTIONS
A39: KOHA DV | H39: Social Sciences | AC39: Screening Question 1
A40: La Croix | H40: Theology and Religious Vocations | AB40: =(1&AB37)*1 -> 1292 | AC40: How do you handle pressure at work especially when meeting deadlines?
A41: Leeward Drive Inn | H41: Transportation and Materials Moving | AC41: Response
A42: Locations Hawaii | H42: Visual and Performing Arts | AC42: Screening Question 2
A43: MAKAI HR | AB43: =(2&AB37)*1 -> 2292 | AC43: What is your specific quality that would make you a good fit for this position?
A44: MANSON | AC44: Response
A45: Military First BNB Solutions | AC45: Screening Question 3
A46: OHANA | AB46: =(3&AB37)*1 -> 3292 | AC46: How comfortable are you working with foreign clients?
A47: OSAKI | AC47: Response
A48: Peak Dental
A49: PEMCO | AA49: =AB49 -> 293 | AB49: =RIGHT(AC49,3)*1 -> 293 | AC49: Job Opening #293
A50: PHARMACARE | AC50: PROFESSIONAL QUESTIONS
A51: PREMIER DENTAL | AC51: Screening Question 1
A52: Premier Supplies | AB52: =(1&AB49)*1 -> 1293 | AC52: How do you handle pressure at work especially when meeting deadlines?
A53: REDHAMMER | AC53: Response
A54: RedHammer/Hawktree | AC54: Screening Question 2
A55: REHAB | AB55: =(2&AB49)*1 -> 2293 | AC55: What is your specific quality that would make you a good fit for this position?
A56: Reyn Spooner | AC56: Response
A57: ServPac | AC57: Screening Question 3
A58: TCA | AB58: =(3&AB49)*1 -> 3293 | AC58: How comfortable are you working with foreign clients?
A59: TEG
A60: Test Record | AA60: =AB60 -> 296 | AB60: =RIGHT(AC60,3)*1 -> 296 | AC60: Job Opening #296
A61: TG ESCROW | AC61: PROFESSIONAL QUESTIONS
A62: TG MARKETING | AC62: Screening Question 1
A63: TG TITLE | AB63: =(1&AB60)*1 -> 1296 | AC63: How do you handle pressure at work especially meeting deadlines?
A64: The Redmont Group | AC64: Response
A65: TIHATI | AC65: Screening Question 2
A66: Tony Auto Group | AB66: =(2&AB60)*1 -> 2296 | AC66: Do you have experience in insurance billing and/or verification?
A67: TORI RICHARD | AC67: Response
A68: Tradewind Charters Hawaii | AC68: Screening Question 3
A69: Trusta | AB69: =(3&AB60)*1 -> 3296 | AC69: Willing to work on a GY shift and on-site setup?
A70: Y. HATA
A71: ZETO | AA71: =AB71 -> 297 | AB71: =RIGHT(AC71,3)*1 -> 297 | AC71: Job Opening #297
AC72: PROFESSIONAL QUESTIONS
AC73: Screening Question 1
AB74: =(1&AB71)*1 -> 1297 | AC74: How comfortable are your working remotely?
AC75: Response
AC76: Screening Question 2
AB77: =(2&AB71)*1 -> 2297 | AC77: Do you have any other applications aside from Connext?
AC78: Response
AC79: Screening Question 3
AB80: =(3&AB71)*1 -> 3297 | AC80: Are you to work from 4pm to 1am, Monday to Friday?
AC81: Response
AA83: =AB83 -> 298 | AB83: =RIGHT(AC83,3)*1 -> 298 | AC83: Job Opening #298
AC84: PROFESSIONAL QUESTIONS
AC85: Screening Question 1
AB86: =(1&AB83)*1 -> 1298 | AC86: Do you have experience as a business writter?
AC87: Response
AC88: Screening Question 2
AB89: =(2&AB83)*1 -> 2298 | AC89: What is your exposure and understanding of the BPO Industry?
AC90: Response
AC91: Screening Question 3
AB92: =(3&AB83)*1 -> 3298 | AC92: How do you think a business journalist can contribute to sales and business development?
AC93: Response
AA95: =AB95 -> 300 | AB95: =RIGHT(AC95,3)*1 -> 300 | AC95: Job Opening #300
AC96: PROFESSIONAL QUESTIONS
AC97: Screening Question 1
AB98: =(1&AB95)*1 -> 1300 | AC98: How many years of optical experience do you have?
AC99: Response
AC100: Screening Question 2
AB101: =(2&AB95)*1 -> 2300 | AC101: Are you amenable to work on night shift?
AC102: Response
...

Sheet Sheet1
A1: </option> | D1: {=_xlfn._xlws.SORT(C2:C42)} | L1: <option value=''></option>
B2: Benefits</option> | C2: =SUBSTITUTE(SUBSTITUTE(SUBSTITUTE(B2,$L$1,""),$L$2,""),$L$3,"") -> Benefits | L2: <option value='Connext Staff'>
B3: Challenge</option> | C3: =SUBSTITUTE(SUBSTITUTE(SUBSTITUTE(B3,$L$1,""),$L$2,""),$L$3,"") -> Challenge | L3: </option>
B4: Culture / Working Environment</option> | C4: =SUBSTITUTE(SUBSTITUTE(SUBSTITUTE(B4,$L$1,""),$L$2,""),$L$3,"") -> Culture / Working Environment
B5: Facility</option> | C5: =SUBSTITUTE(SUBSTITUTE(SUBSTITUTE(B5,$L$1,""),$L$2,""),$L$3,"") -> Facility
B6: Jobs within Field</option> | C6: =SUBSTITUTE(SUBSTITUTE(SUBSTITUTE(B6,$L$1,""),$L$2,""),$L$3,"") -> Jobs within Field
B7: Just Need a Job / Applied Various Places</option> | C7: =SUBSTITUTE(SUBSTITUTE(SUBSTITUTE(B7,$L$1,""),$L$2,""),$L$3,"") -> Just Need a Job / Applied Various Places
B8: Location or Convenience</option> | C8: =SUBSTITUTE(SUBSTITUTE(SUBSTITUTE(B8,$L$1,""),$L$2,""),$L$3,"") -> Location or Convenience
B9: Recognition and Growth</option> | C9: =SUBSTITUTE(SUBSTITUTE(SUBSTITUTE(B9,$L$1,""),$L$2,""),$L$3,"") -> Recognition and Growth
B10: Referred by Family or Friend</option> | C10: =SUBSTITUTE(SUBSTITUTE(SUBSTITUTE(B10,$L$1,""),$L$2,""),$L$3,"") -> Referred by Family or Friend
B11: Reputation and Brand</option> | C11: =SUBSTITUTE(SUBSTITUTE(SUBSTITUTE(B11,$L$1,""),$L$2,""),$L$3,"") -> Reputation and Brand
B12: Salary</option> | C12: =SUBSTITUTE(SUBSTITUTE(SUBSTITUTE(B12,$L$1,""),$L$2,""),$L$3,"") -> Salary
B13: Working Hours</option> | C13: =SUBSTITUTE(SUBSTITUTE(SUBSTITUTE(B13,$L$1,""),$L$2,""),$L$3,"") -> Working Hours
C14: =SUBSTITUTE(SUBSTITUTE(SUBSTITUTE(B14,$L$1,""),$L$2,""),$L$3,"")
C15: =SUBSTITUTE(SUBSTITUTE(SUBSTITUTE(B15,$L$1,""),$L$2,""),$L$3,"")
C16: =SUBSTITUTE(SUBSTITUTE(SUBSTITUTE(B16,$L$1,""),$L$2,""),$L$3,"")
C17: =SUBSTITUTE(SUBSTITUTE(SUBSTITUTE(B17,$L$1,""),$L$2,""),$L$3,"")
C18: =SUBSTITUTE(SUBSTITUTE(SUBSTITUTE(B18,$L$1,""),$L$2,""),$L$3,"")
C19: =SUBSTITUTE(SUBSTITUTE(SUBSTITUTE(B19,$L$1,""),$L$2,""),$L$3,"")
C20: =SUBSTITUTE(SUBSTITUTE(SUBSTITUTE(B20,$L$1,""),$L$2,""),$L$3,"")
C21: =SUBSTITUTE(SUBSTITUTE(SUBSTITUTE(B21,$L$1,""),$L$2,""),$L$3,"")
C22: =SUBSTITUTE(SUBSTITUTE(SUBSTITUTE(B22,$L$1,""),$L$2,""),$L$3,"")
C23: =SUBSTITUTE(SUBSTITUTE(SUBSTITUTE(B23,$L$1,""),$L$2,""),$L$3,"")
C24: =SUBSTITUTE(SUBSTITUTE(SUBSTITUTE(B24,$L$1,""),$L$2,""),$L$3,"")
C25: =SUBSTITUTE(SUBSTITUTE(SUBSTITUTE(B25,$L$1,""),$L$2,""),$L$3,"")
... C29: =SUBSTITUTE(SUBSTITUTE(SUBSTITUTE(B29,$L$1,""),$L$2,""),$L$3,"")
C30: =SUBSTITUTE(SUBSTITUTE(SUBSTITUTE(B30,$L$1,""),$L$2,""),$L$3,"") | D30: Benefits
C31: =SUBSTITUTE(SUBSTITUTE(SUBSTITUTE(B31,$L$1,""),$L$2,""),$L$3,"") | D31: Challenge
C32: =SUBSTITUTE(SUBSTITUTE(SUBSTITUTE(B32,$L$1,""),$L$2,""),$L$3,"") | D32: Culture / Working Environment
C33: =SUBSTITUTE(SUBSTITUTE(SUBSTITUTE(B33,$L$1,""),$L$2,""),$L$3,"") | D33: Facility
C34: =SUBSTITUTE(SUBSTITUTE(SUBSTITUTE(B34,$L$1,""),$L$2,""),$L$3,"") | D34: Jobs within Field
C35: =SUBSTITUTE(SUBSTITUTE(SUBSTITUTE(B35,$L$1,""),$L$2,""),$L$3,"") | D35: Just Need a Job / Applied Various Places
C36: =SUBSTITUTE(SUBSTITUTE(SUBSTITUTE(B36,$L$1,""),$L$2,""),$L$3,"") | D36: Location or Convenience
C37: =SUBSTITUTE(SUBSTITUTE(SUBSTITUTE(B37,$L$1,""),$L$2,""),$L$3,"") | D37: Recognition and Growth
C38: =SUBSTITUTE(SUBSTITUTE(SUBSTITUTE(B38,$L$1,""),$L$2,""),$L$3,"") | D38: Referred by Family or Friend
C39: =SUBSTITUTE(SUBSTITUTE(SUBSTITUTE(B39,$L$1,""),$L$2,""),$L$3,"") | D39: Reputation and Brand
C40: =SUBSTITUTE(SUBSTITUTE(SUBSTITUTE(B40,$L$1,""),$L$2,""),$L$3,"") | D40: Salary
C41: =SUBSTITUTE(SUBSTITUTE(SUBSTITUTE(B41,$L$1,""),$L$2,""),$L$3,"") | D41: Working Hours
C42: =SUBSTITUTE(SUBSTITUTE(SUBSTITUTE(B42,$L$1,""),$L$2,""),$L$3,"")
C43: =SUBSTITUTE(SUBSTITUTE(SUBSTITUTE(B43,$L$1,""),$L$2,""),$L$3,"")
C44: =SUBSTITUTE(SUBSTITUTE(SUBSTITUTE(B44,$L$1,""),$L$2,""),$L$3,"")
C45: =SUBSTITUTE(SUBSTITUTE(SUBSTITUTE(B45,$L$1,""),$L$2,""),$L$3,"")
C46: =SUBSTITUTE(SUBSTITUTE(SUBSTITUTE(B46,$L$1,""),$L$2,""),$L$3,"")
C47: =SUBSTITUTE(SUBSTITUTE(SUBSTITUTE(B47,$L$1,""),$L$2,""),$L$3,"")
C48: =SUBSTITUTE(SUBSTITUTE(SUBSTITUTE(B48,$L$1,""),$L$2,""),$L$3,"")
C49: =SUBSTITUTE(SUBSTITUTE(SUBSTITUTE(B49,$L$1,""),$L$2,""),$L$3,"")
C50: =SUBSTITUTE(SUBSTITUTE(SUBSTITUTE(B50,$L$1,""),$L$2,""),$L$3,"")
C51: =SUBSTITUTE(SUBSTITUTE(SUBSTITUTE(B51,$L$1,""),$L$2,""),$L$3,"")
C52: =SUBSTITUTE(SUBSTITUTE(SUBSTITUTE(B52,$L$1,""),$L$2,""),$L$3,"")
C53: =SUBSTITUTE(SUBSTITUTE(SUBSTITUTE(B53,$L$1,""),$L$2,""),$L$3,"")
... C73: =SUBSTITUTE(SUBSTITUTE(SUBSTITUTE(B73,$L$1,""),$L$2,""),$L$3,"")
